ia_markov/.markov.py.swp
ia_markov/__init__.py
ia_markov/markov.py
ia_markov-0.3.1.dist-info/METADATA
ia_markov-0.3.1.dist-info/RECORD
ia_markov-0.3.1.dist-info/WHEEL
ia_markov-0.3.1.dist-info/top_level.txt
