Metadata-Version: 2.1
Name: ia-markov
Version: 0.3.1
Summary: A Markov model trained on Internet Archive text files.
Home-page: https://github.com/accraze/python-ia-markov
Author: Andy Craze
Author-email: accraze@gmail.com
License: BSD
Keywords: markov,text,internetarchive,model,nlp,corpus
Platform: UNKNOWN
Classifier: Development Status :: 5 - Production/Stable
Classifier: Intended Audience :: Developers
Classifier: License :: OSI Approved :: BSD License
Classifier: Operating System :: Unix
Classifier: Operating System :: POSIX
Classifier: Programming Language :: Python
Classifier: Programming Language :: Python :: 3
Classifier: Programming Language :: Python :: 3.3
Classifier: Programming Language :: Python :: 3.4
Classifier: Programming Language :: Python :: 3.5
Classifier: Topic :: Utilities
Requires-Dist: markovify (==0.7.1)
Requires-Dist: spacy (==2.0.12)
Requires-Dist: internetarchive (==1.8.1)
